{
  "fetchedAt": "2026-07-22T14:21:50.956Z",
  "league": "Runes of Aldur",
  "realm": "poe2",
  "unit": "exalted",
  "prices": {
    "divine": {
      "ex": 432.09,
      "source": "Leagues.DivinePrice"
    },
    "exalt": {
      "ex": 1,
      "source": "Exalted Orb"
    },
    "greaterExalt": {
      "ex": 4.58,
      "source": "Greater Exalted Orb"
    },
    "regal": {
      "ex": 0.74,
      "source": "Regal Orb"
    },
    "chaos": {
      "ex": 56.12,
      "source": "Chaos Orb"
    },
    "annul": {
      "ex": 225.9,
      "source": "Orb of Annulment"
    },
    "fracturing": {
      "ex": 4634.55,
      "source": "Fracturing Orb"
    },
    "artificer": {
      "ex": 0.77,
      "source": "Artificer's Orb"
    },
    "putrefaction": {
      "ex": 0.2,
      "source": "Omen of Putrefaction"
    },
    "echoes": {
      "ex": 152.65,
      "source": "Omen of Abyssal Echoes"
    },
    "necromancy": {
      "ex": 2.86,
      "source": "Omen of Sinistral Necromancy / Omen of Dextral Necromancy"
    },
    "light": {
      "ex": 5923.08,
      "source": "Omen of Light"
    },
    "dirExalt": {
      "ex": 9.48,
      "source": "Omen of Sinistral Exaltation / Omen of Dextral Exaltation"
    },
    "whittling": {
      "ex": 4628.02,
      "source": "Omen of Whittling"
    },
    "rib": {
      "ex": 2.12,
      "source": "Preserved Rib"
    },
    "boneJewel": {
      "ex": 37.69,
      "source": "Preserved Collarbone"
    }
  },
  "missing": []
}