{
  "fetchedAt": "2026-07-13T21:12:49.280Z",
  "league": "Runes of Aldur",
  "realm": "poe2",
  "unit": "exalted",
  "prices": {
    "divine": {
      "ex": 510.47,
      "source": "Leagues.DivinePrice"
    },
    "exalt": {
      "ex": 1,
      "source": "Exalted Orb"
    },
    "greaterExalt": {
      "ex": 4.78,
      "source": "Greater Exalted Orb"
    },
    "regal": {
      "ex": 0.78,
      "source": "Regal Orb"
    },
    "chaos": {
      "ex": 63.97,
      "source": "Chaos Orb"
    },
    "annul": {
      "ex": 390.44,
      "source": "Orb of Annulment"
    },
    "fracturing": {
      "ex": 5356.21,
      "source": "Fracturing Orb"
    },
    "artificer": {
      "ex": 1.89,
      "source": "Artificer's Orb"
    },
    "putrefaction": {
      "ex": 0.71,
      "source": "Omen of Putrefaction"
    },
    "echoes": {
      "ex": 94.32,
      "source": "Omen of Abyssal Echoes"
    },
    "necromancy": {
      "ex": 6.89,
      "source": "Omen of Sinistral Necromancy / Omen of Dextral Necromancy"
    },
    "light": {
      "ex": 4946.13,
      "source": "Omen of Light"
    },
    "dirExalt": {
      "ex": 25.19,
      "source": "Omen of Sinistral Exaltation / Omen of Dextral Exaltation"
    },
    "whittling": {
      "ex": 4865.69,
      "source": "Omen of Whittling"
    },
    "rib": {
      "ex": 1.42,
      "source": "Preserved Rib"
    },
    "boneJewel": {
      "ex": 16.62,
      "source": "Preserved Collarbone"
    }
  },
  "missing": []
}