{
  "fetchedAt": "2026-07-22T06:42:06.639Z",
  "league": "Runes of Aldur",
  "realm": "poe2",
  "unit": "exalted",
  "prices": {
    "divine": {
      "ex": 414.14,
      "source": "Leagues.DivinePrice"
    },
    "exalt": {
      "ex": 1,
      "source": "Exalted Orb"
    },
    "greaterExalt": {
      "ex": 4.95,
      "source": "Greater Exalted Orb"
    },
    "regal": {
      "ex": 0.43,
      "source": "Regal Orb"
    },
    "chaos": {
      "ex": 55.8,
      "source": "Chaos Orb"
    },
    "annul": {
      "ex": 227.6,
      "source": "Orb of Annulment"
    },
    "fracturing": {
      "ex": 4651.36,
      "source": "Fracturing Orb"
    },
    "artificer": {
      "ex": 1.46,
      "source": "Artificer's Orb"
    },
    "putrefaction": {
      "ex": 0.23,
      "source": "Omen of Putrefaction"
    },
    "echoes": {
      "ex": 177.83,
      "source": "Omen of Abyssal Echoes"
    },
    "necromancy": {
      "ex": 2.7,
      "source": "Omen of Sinistral Necromancy / Omen of Dextral Necromancy"
    },
    "light": {
      "ex": 5689.99,
      "source": "Omen of Light"
    },
    "dirExalt": {
      "ex": 10.25,
      "source": "Omen of Sinistral Exaltation / Omen of Dextral Exaltation"
    },
    "whittling": {
      "ex": 4673.25,
      "source": "Omen of Whittling"
    },
    "rib": {
      "ex": 2.13,
      "source": "Preserved Rib"
    },
    "boneJewel": {
      "ex": 40.18,
      "source": "Preserved Collarbone"
    }
  },
  "missing": []
}