{
  "fetchedAt": "2026-07-22T22:15:49.453Z",
  "league": "Runes of Aldur",
  "realm": "poe2",
  "unit": "exalted",
  "prices": {
    "divine": {
      "ex": 415.03,
      "source": "Leagues.DivinePrice"
    },
    "exalt": {
      "ex": 1,
      "source": "Exalted Orb"
    },
    "greaterExalt": {
      "ex": 4.85,
      "source": "Greater Exalted Orb"
    },
    "regal": {
      "ex": 0.58,
      "source": "Regal Orb"
    },
    "chaos": {
      "ex": 52.65,
      "source": "Chaos Orb"
    },
    "annul": {
      "ex": 196.42,
      "source": "Orb of Annulment"
    },
    "fracturing": {
      "ex": 4274.83,
      "source": "Fracturing Orb"
    },
    "artificer": {
      "ex": 1.38,
      "source": "Artificer's Orb"
    },
    "putrefaction": {
      "ex": 1.21,
      "source": "Omen of Putrefaction"
    },
    "echoes": {
      "ex": 129.59,
      "source": "Omen of Abyssal Echoes"
    },
    "necromancy": {
      "ex": 3.05,
      "source": "Omen of Sinistral Necromancy / Omen of Dextral Necromancy"
    },
    "light": {
      "ex": 5636.96,
      "source": "Omen of Light"
    },
    "dirExalt": {
      "ex": 9.03,
      "source": "Omen of Sinistral Exaltation / Omen of Dextral Exaltation"
    },
    "whittling": {
      "ex": 4262.52,
      "source": "Omen of Whittling"
    },
    "rib": {
      "ex": 3.03,
      "source": "Preserved Rib"
    },
    "boneJewel": {
      "ex": 40.3,
      "source": "Preserved Collarbone"
    }
  },
  "missing": []
}